pyprojectviz/__main__.py
pyprojectviz/code_analyzer/__init__.py
pyprojectviz/config.py
pyprojectviz/utils.py
pyprojectviz-0.1.1.dist-info/LICENSE
pyprojectviz-0.1.1.dist-info/METADATA
pyprojectviz-0.1.1.dist-info/WHEEL
pyprojectviz-0.1.1.dist-info/RECORD
