Metadata-Version: 2.1
Name: pyprojectviz
Version: 0.1.1
Summary: Visualizes classes and methods in a Python project
License: MIT
Author: codekuu
Author-email: hello-pyprojectviz@inaktiverad.se
Requires-Python: >=3.8,<4.0
Classifier: License :: OSI Approved :: MIT License
Classifier: Programming Language :: Python :: 3
Classifier: Programming Language :: Python :: 3.8
Classifier: Programming Language :: Python :: 3.9
Classifier: Programming Language :: Python :: 3.10
Classifier: Programming Language :: Python :: 3.11
Requires-Dist: graphviz (>=0.20.1,<0.21.0)
Requires-Dist: pydantic (>=2.5.2,<3.0.0)
Requires-Dist: pyyaml (>=6.0.1,<7.0.0)
Requires-Dist: typer (>=0.9.0,<0.10.0)
